itaxotools/__pyinstaller/hook-itaxotools.hapsolutely.py
itaxotools/hapsolutely/__init__.py
itaxotools/hapsolutely/app.py
itaxotools/hapsolutely/config.py
itaxotools/hapsolutely/fitchi.py
itaxotools/hapsolutely/resources.py
itaxotools/hapsolutely/yamlify.py
itaxotools/hapsolutely/documents/about.html
itaxotools/hapsolutely/documents/nets.html
itaxotools/hapsolutely/documents/phase.html
itaxotools/hapsolutely/graphics/about.svg
itaxotools/hapsolutely/graphics/nets.svg
itaxotools/hapsolutely/graphics/phase.svg
itaxotools/hapsolutely/graphics/stats.svg
itaxotools/hapsolutely/icons/edge_style.svg
itaxotools/hapsolutely/icons/export.svg
itaxotools/hapsolutely/icons/font.svg
itaxotools/hapsolutely/icons/haploweb.svg
itaxotools/hapsolutely/icons/legend.svg
itaxotools/hapsolutely/icons/lock_distances.svg
itaxotools/hapsolutely/icons/lock_labels.svg
itaxotools/hapsolutely/icons/panel.svg
itaxotools/hapsolutely/icons/pen.svg
itaxotools/hapsolutely/icons/redo.svg
itaxotools/hapsolutely/icons/resize_edge.svg
itaxotools/hapsolutely/icons/resize_node.svg
itaxotools/hapsolutely/icons/rotate.svg
itaxotools/hapsolutely/icons/scale.svg
itaxotools/hapsolutely/icons/scheme.svg
itaxotools/hapsolutely/icons/singletons.svg
itaxotools/hapsolutely/icons/snap.svg
itaxotools/hapsolutely/icons/template.svg
itaxotools/hapsolutely/icons/undo.svg
itaxotools/hapsolutely/icons/zoom.svg
itaxotools/hapsolutely/logos/hapsolutely.ico
itaxotools/hapsolutely/logos/hapsolutely.svg
itaxotools/hapsolutely/logos/hapsolutely_h.svg
itaxotools/hapsolutely/model/phased_results.py
itaxotools/hapsolutely/model/phased_sequence.py
itaxotools/hapsolutely/tasks/about/__init__.py
itaxotools/hapsolutely/tasks/about/model.py
itaxotools/hapsolutely/tasks/about/view.py
itaxotools/hapsolutely/tasks/common/model.py
itaxotools/hapsolutely/tasks/common/types.py
itaxotools/hapsolutely/tasks/common/view.py
itaxotools/hapsolutely/tasks/common/work.py
itaxotools/hapsolutely/tasks/convphase/__init__.py
itaxotools_hapsolutely-0.2.3.dist-info/licenses/LICENSE.txt
itaxotools_hapsolutely-0.2.3.dist-info/METADATA
itaxotools_hapsolutely-0.2.3.dist-info/WHEEL
itaxotools_hapsolutely-0.2.3.dist-info/entry_points.txt
itaxotools_hapsolutely-0.2.3.dist-info/top_level.txt
itaxotools_hapsolutely-0.2.3.dist-info/RECORD
