Metadata-Version: 2.4
Name: itaxotools-hapsolutely
Version: 0.2.3
Summary: Reconstruct haplotypes and produce genealogy graphs from population data
Author-email: Stefanos Patmanidis <stefanpatman91@gmail.com>
Project-URL: Homepage, https://itaxotools.org/
Project-URL: Source, https://github.com/iTaxoTools/Hapsolutely
Classifier: License :: OSI Approved :: GNU General Public License v3 or later (GPLv3+)
Classifier: Development Status :: 5 - Production/Stable
Classifier: Programming Language :: Python
Classifier: Programming Language :: Python :: 3.10
Classifier: Programming Language :: Python :: 3.11
Classifier: Programming Language :: Python :: 3.12
Classifier: Programming Language :: Python :: Implementation :: CPython
Requires-Python: <4,>=3.10.2
License-File: LICENSE.txt
Requires-Dist: itaxotools-common
Requires-Dist: itaxotools-convphase
Requires-Dist: itaxotools-popart-networks
Requires-Dist: itaxotools-taxi2
Requires-Dist: itaxotools-fitchi
Requires-Dist: itaxotools-haplostats
Requires-Dist: itaxotools-haplodemo
Requires-Dist: itaxotools-taxi-gui
Requires-Dist: itaxotools-convphase-gui
Requires-Dist: pyside6<6.9.0
Requires-Dist: biopython
Requires-Dist: pyyaml
Provides-Extra: dev
Requires-Dist: setuptools-scm; extra == "dev"
Requires-Dist: pre-commit; extra == "dev"
Requires-Dist: ruff; extra == "dev"
Requires-Dist: pytest; extra == "dev"
Requires-Dist: pytest-qt; extra == "dev"
Requires-Dist: pytest-xvfb; extra == "dev"
Requires-Dist: pyinstaller; extra == "dev"
Dynamic: license-file
